encron/__init__.py
encron/tools.py
encron-1.0.0.dist-info/LICENSE
encron-1.0.0.dist-info/METADATA
encron-1.0.0.dist-info/WHEEL
encron-1.0.0.dist-info/top_level.txt
encron-1.0.0.dist-info/RECORD
