Metadata-Version: 2.1
Name: encron
Version: 1.0.0
Summary: Super encryption and decryption tool that works well on both system and web
Author-email: Aston Kariuki <astonmwendwa254@gmail.com>
Classifier: Programming Language :: Python :: 3
Classifier: License :: OSI Approved :: MIT License
Classifier: Operating System :: OS Independent
Requires-Python: >=3.8
License-File: LICENSE
Requires-Dist: cryptography
